sclera/__init__.py
sclera/tasks/__init__.py
sclera/tasks/depth_estimation/__init__.py
sclera/tasks/depth_estimation/models/__init__.py
sclera/tasks/depth_estimation/models/fastmde.py
sclera/tasks/semantic_segmentation/__init__.py
sclera/tasks/semantic_segmentation/models/__init__.py
sclera/tasks/semantic_segmentation/models/segformer.py
sclera/tasks/semantic_segmentation/models/unet.py
sclera-0.1.7.dist-info/LICENSE
sclera-0.1.7.dist-info/METADATA
sclera-0.1.7.dist-info/WHEEL
sclera-0.1.7.dist-info/RECORD
