Metadata-Version: 2.1
Name: sclera
Version: 0.1.7
Summary: One-stop destination for Computer Vision with Keras
Author: Suvaditya Mukherjee
Author-email: suvadityamuk@gmail.com
Requires-Python: >=3.10,<4.0
Classifier: Programming Language :: Python :: 3
Classifier: Programming Language :: Python :: 3.10
Classifier: Programming Language :: Python :: 3.11
Requires-Dist: keras (>=2.14.0,<3.0.0)
Requires-Dist: keras-core (>=0.1.7,<0.2.0)
